memory_block_ipa/ram.v
`timescale 1ns / 1ps
module RAM(mem_addr,mem_data,rd,wr,valM);

    input [63:0] mem_addr;
    input [63:0] mem_data;
    input rd;
    input wr;
    output reg[63:0] valM;
    reg [63:0] mem [8191:0];

    always @ (wr,rd,mem_data,mem_addr)
    begin
        if (wr && !rd) mem[mem_addr] = mem_data;
        if (rd && !wr) valM = mem[mem_addr];
    end
endmodule

module Mem_read(icode,rd);
    input[3:0] icode;
    output reg rd;

    always @(icode)
    begin
        case(icode)
            4'h5,4'hB,4'h9:
                rd <= 1'b1;
            default: rd <= 1'b0;
        endcase
    end
endmodule

module Mem_write(icode,wr);
    input[3:0] icode;
    output reg wr;

    always @(icode)
    begin
        case(icode)
            4'h4,4'hA,4'h8:
                wr <= 1'b1;
            default: wr <= 1'b0;
        endcase
    end
endmodule

module Mem_addr(icode,valE,valA,mem_addr);
    input[3:0] icode;
    output reg[63:0] mem_addr;
    input[63:0] valE;
    input[63:0] valA;

    always @(icode,valA,valE)
    begin
        case(icode)
            4'h4,4'h5,4'h8,4'hA:
                mem_addr <= valE;
            4'h9,4'hB:
                mem_addr <= valA;
        endcase
    end
endmodule

module Mem_data(icode,valA,valP,mem_data);
    input[3:0] icode;
    output reg[63:0] mem_data;
    input[63:0] valP;
    input[63:0] valA;

    always @(icode,valA,valP)
    begin
        case(icode)
            4'h4,4'hA:
                mem_data <= valA;
            4'h8:
                mem_data <= valP;
        endcase
    end
endmodule

memory_block_ipa/ram_test.v
`timescale 1ns / 1ps
module ram_test;

    reg [3:0] icode;
    wire [63:0] mem_addr;
    wire [63:0] mem_data;
    reg [63:0] valE;
    reg [63:0] valA;
    reg [63:0] valP;
    wire [63:0] valM;
    wire rd;
    wire wr;

    RAM ram1(.mem_addr(mem_addr),.mem_data(mem_data),.rd(rd),.wr(wr),.valM(valM));
    Mem_read Mr(.icode(icode),.rd(rd));
    Mem_write Mw(.icode(icode),.wr(wr));
    Mem_addr Ma(.icode(icode),.valA(valA),.valE(valE),.mem_addr(mem_addr));
    Mem_data Md(.icode(icode),.valA(valA),.valP(valP),.mem_data(mem_data));    

    
    integer k;
    parameter base_addr = 64'hFF;

    
    initial begin
    $dumpfile("ram_test.vcd");
    $dumpvars(0,ram_test);

    
    for(k=0;k<10;k++)
    begin
        icode <= 4'h4;
        valE  <= k + base_addr;
        valA  <= k+ $random;
        #10;
    end

    for(k=0;k<10;k++)
    begin
        icode <= 4'h5;
        valE  <= k + base_addr;
        #10;
    end

    #20 $finish;
        
    end

    
    


endmodule

sequential/memory-stage/ram_test.vcd
$date
	Tue Mar  2 01:23:13 2021
$end
$version
	Icarus Verilog
$end
$timescale
	1ps
$end
$scope module ram_test $end
$var wire 1 ! wr $end
$var wire 64 " valM [63:0] $end
$var wire 1 # rd $end
$var wire 64 $ mem_data [63:0] $end
$var wire 64 % mem_addr [63:0] $end
$var reg 4 & icode [3:0] $end
$var reg 64 ' valA [63:0] $end
$var reg 64 ( valE [63:0] $end
$var reg 64 ) valP [63:0] $end
$var integer 32 * k [31:0] $end
$scope module Ma $end
$var wire 4 + icode [3:0] $end
$var wire 64 , valA [63:0] $end
$var wire 64 - valE [63:0] $end
$var reg 64 . mem_addr [63:0] $end
$upscope $end
$scope module Md $end
$var wire 4 / icode [3:0] $end
$var wire 64 0 valA [63:0] $end
$var wire 64 1 valP [63:0] $end
$var reg 64 2 mem_data [63:0] $end
$upscope $end
$scope module Mr $end
$var wire 4 3 icode [3:0] $end
$var reg 1 # rd $end
$upscope $end
$scope module Mw $end
$var wire 4 4 icode [3:0] $end
$var reg 1 ! wr $end
$upscope $end
$scope module ram1 $end
$var wire 64 5 mem_addr [63:0] $end
$var wire 64 6 mem_data [63:0] $end
$var wire 1 # rd $end
$var wire 1 ! wr $end
$var reg 64 7 valM [63:0] $end
$upscope $end
$upscope $end
$enddefinitions $end
#0
$dumpvars
bx 7
b10010000101010011010100100100 6
b11111111 5
b100 4
b100 3
b10010000101010011010100100100 2
bx 1
b10010000101010011010100100100 0
b100 /
b11111111 .
b11111111 -
b10010000101010011010100100100 ,
b100 +
b0 *
bx )
b11111111 (
b10010000101010011010100100100 '
b100 &
b11111111 %
b10010000101010011010100100100 $
0#
bx "
1!
$end
#10000
b1111111111111111111111111111111111000000100010010101111010000010 $
b1111111111111111111111111111111111000000100010010101111010000010 2
b1111111111111111111111111111111111000000100010010101111010000010 6
b100000000 %
b100000000 .
b100000000 5
b1111111111111111111111111111111111000000100010010101111010000010 '
b1111111111111111111111111111111111000000100010010101111010000010 ,
b1111111111111111111111111111111111000000100010010101111010000010 0
b100000000 (
b100000000 -
b1 *
#20000
b1111111111111111111111111111111110000100100001001101011000001011 $
b1111111111111111111111111111111110000100100001001101011000001011 2
b1111111111111111111111111111111110000100100001001101011000001011 6
b100000001 %
b100000001 .
b100000001 5
b1111111111111111111111111111111110000100100001001101011000001011 '
b1111111111111111111111111111111110000100100001001101011000001011 ,
b1111111111111111111111111111111110000100100001001101011000001011 0
b100000001 (
b100000001 -
b10 *
#30000
b1111111111111111111111111111111110110001111100000101011001100110 $
b1111111111111111111111111111111110110001111100000101011001100110 2
b1111111111111111111111111111111110110001111100000101011001100110 6
b100000010 %
b100000010 .
b100000010 5
b1111111111111111111111111111111110110001111100000101011001100110 '
b1111111111111111111111111111111110110001111100000101011001100110 ,
b1111111111111111111111111111111110110001111100000101011001100110 0
b100000010 (
b100000010 -
b11 *
#40000
b110101110010111101100010001 $
b110101110010111101100010001 2
b110101110010111101100010001 6
b100000011 %
b100000011 .
b100000011 5
b110101110010111101100010001 '
b110101110010111101100010001 ,
b110101110010111101100010001 0
b100000011 (
b100000011 -
b100 *
#50000
b1000110110111111001100110010010 $
b1000110110111111001100110010010 2
b1000110110111111001100110010010 6
b100000100 %
b100000100 .
b100000100 5
b1000110110111111001100110010010 '
b1000110110111111001100110010010 ,
b1000110110111111001100110010010 0
b100000100 (
b100000100 -
b101 *
#60000
b1111111111111111111111111111111110110010110000101000010001101011 $
b1111111111111111111111111111111110110010110000101000010001101011 2
b1111111111111111111111111111111110110010110000101000010001101011 6
b100000101 %
b100000101 .
b100000101 5
b1111111111111111111111111111111110110010110000101000010001101011 '
b1111111111111111111111111111111110110010110000101000010001101011 ,
b1111111111111111111111111111111110110010110000101000010001101011 0
b100000101 (
b100000101 -
b110 *
#70000
b1111111111111111111111111111111110001001001101110101001000011001 $
b1111111111111111111111111111111110001001001101110101001000011001 2
b1111111111111111111111111111111110001001001101110101001000011001 6
b100000110 %
b100000110 .
b100000110 5
b1111111111111111111111111111111110001001001101110101001000011001 '
b1111111111111111111111111111111110001001001101110101001000011001 ,
b1111111111111111111111111111111110001001001101110101001000011001 0
b100000110 (
b100000110 -
b111 *
#80000
b111100111110001100001001 $
b111100111110001100001001 2
b111100111110001100001001 6
b100000111 %
b100000111 .
b100000111 5
b111100111110001100001001 '
b111100111110001100001001 ,
b111100111110001100001001 0
b100000111 (
b100000111 -
b1000 *
#90000
b110110101111100110100010110 $
b110110101111100110100010110 2
b110110101111100110100010110 6
b100001000 %
b100001000 .
b100001000 5
b110110101111100110100010110 '
b110110101111100110100010110 ,
b110110101111100110100010110 0
b100001000 (
b100001000 -
b1001 *
#100000
b10010000101010011010100100100 "
b10010000101010011010100100100 7
b11111111 %
b11111111 .
b11111111 5
1#
0!
b11111111 (
b11111111 -
b101 &
b101 +
b101 /
b101 3
b101 4
b0 *
#110000
b1111111111111111111111111111111111000000100010010101111010000010 "
b1111111111111111111111111111111111000000100010010101111010000010 7
b100000000 %
b100000000 .
b100000000 5
b100000000 (
b100000000 -
b1 *
#120000
b1111111111111111111111111111111110000100100001001101011000001011 "
b1111111111111111111111111111111110000100100001001101011000001011 7
b100000001 %
b100000001 .
b100000001 5
b100000001 (
b100000001 -
b10 *
#130000
b1111111111111111111111111111111110110001111100000101011001100110 "
b1111111111111111111111111111111110110001111100000101011001100110 7
b100000010 %
b100000010 .
b100000010 5
b100000010 (
b100000010 -
b11 *
#140000
b110101110010111101100010001 "
b110101110010111101100010001 7
b100000011 %
b100000011 .
b100000011 5
b100000011 (
b100000011 -
b100 *
#150000
b1000110110111111001100110010010 "
b1000110110111111001100110010010 7
b100000100 %
b100000100 .
b100000100 5
b100000100 (
b100000100 -
b101 *
#160000
b1111111111111111111111111111111110110010110000101000010001101011 "
b1111111111111111111111111111111110110010110000101000010001101011 7
b100000101 %
b100000101 .
b100000101 5
b100000101 (
b100000101 -
b110 *
#170000
b1111111111111111111111111111111110001001001101110101001000011001 "
b1111111111111111111111111111111110001001001101110101001000011001 7
b100000110 %
b100000110 .
b100000110 5
b100000110 (
b100000110 -
b111 *
#180000
b111100111110001100001001 "
b111100111110001100001001 7
b100000111 %
b100000111 .
b100000111 5
b100000111 (
b100000111 -
b1000 *
#190000
b110110101111100110100010110 "
b110110101111100110100010110 7
b100001000 %
b100001000 .
b100001000 5
b100001000 (
b100001000 -
b1001 *
#200000
b1010 *
