memory_block_ipa/ram.v
`timescale 1ns / 1ps
module ram(addr,data_in,clk,rd,wr,data_out);

    input [9:0] addr;
    input [31:0] data_in;
    input clk;
    input rd;
    input wr;
    output reg[31:0] data_out;
    reg [31:0] mem [1023:0];

    always @ (posedge clk)
        if (wr && !rd) mem[addr] = data_in;
    
    always @ (posedge clk)
        if (rd && !wr) data_out = mem[addr];
endmodule

memory_block_ipa/ram_test.v
`timescale 1ns / 1ps
module ram_test;
    reg [9:0] addr;
    wire [31:0] data_out;
    reg [31:0] data_in;
    reg write, read;
    integer k;
    reg clk = 1'b0;

    ram  ram_1(.addr(addr),.data_in(data_in),.data_out(data_out),.clk(clk),.rd(read),.wr(write));

    initial begin
    $dumpfile("ram_test.vcd");
    $dumpvars(0,ram_test);

    for (k=0;k<=1023;k=k+1)
        begin
            data_in = (k+k)%256;
            read = 0;
            write = 1;
            addr = k;
            #20;
        end
    write = 0;
    repeat (20)
        begin
        addr = $random % 1024;
        read = 1;
        write = 0;
        # 20;
        end
        #20 $finish;
        
    end

    always #10 clk = ~clk;
    
    


endmodule

memory_block_ipa/ram_test.vcd
$date
	Tue Feb  9 17:48:20 2021
$end
$version
	Icarus Verilog
$end
$timescale
	1ps
$end
$scope module ram_test $end
$var wire 32 ! data_out [31:0] $end
$var reg 10 " addr [9:0] $end
$var reg 1 # clk $end
$var reg 32 $ data_in [31:0] $end
$var reg 1 % read $end
$var reg 1 & write $end
$var integer 32 ' k [31:0] $end
$scope module ram_1 $end
$var wire 10 ( addr [9:0] $end
$var wire 1 # clk $end
$var wire 32 ) data_in [31:0] $end
$var wire 1 % rd $end
$var wire 1 & wr $end
$var reg 32 * data_out [31:0] $end
$upscope $end
$upscope $end
$enddefinitions $end
#0
$dumpvars
bx *
b0 )
b0 (
b0 '
1&
0%
b0 $
0#
b0 "
bx !
$end
#10000
1#
#20000
0#
b1 "
b1 (
b10 $
b10 )
b1 '
#30000
1#
#40000
0#
b10 "
b10 (
b100 $
b100 )
b10 '
#50000
1#
#60000
0#
b11 "
b11 (
b110 $
b110 )
b11 '
#70000
1#
#80000
0#
b100 "
b100 (
b1000 $
b1000 )
b100 '
#90000
1#
#100000
0#
b101 "
b101 (
b1010 $
b1010 )
b101 '
#110000
1#
#120000
0#
b110 "
b110 (
b1100 $
b1100 )
b110 '
#130000
1#
#140000
0#
b111 "
b111 (
b1110 $
b1110 )
b111 '
#150000
1#
#160000
0#
b1000 "
b1000 (
b10000 $
b10000 )
b1000 '
#170000
1#
#180000
0#
b1001 "
b1001 (
b10010 $
b10010 )
b1001 '
#190000
1#
#200000
0#
b1010 "
b1010 (
b10100 $
b10100 )
b1010 '
#210000
1#
#220000
0#
b1011 "
b1011 (
b10110 $
b10110 )
b1011 '
#230000
1#
#240000
0#
b1100 "
b1100 (
b11000 $
b11000 )
b1100 '
#250000
1#
#260000
0#
b1101 "
b1101 (
b11010 $
b11010 )
b1101 '
#270000
1#
#280000
0#
b1110 "
b1110 (
b11100 $
b11100 )
b1110 '
#290000
1#
#300000
0#
b1111 "
b1111 (
b11110 $
b11110 )
b1111 '
#310000
1#
#320000
0#
b10000 "
b10000 (
b100000 $
b100000 )
b10000 '
#330000
1#
#340000
0#
b10001 "
b10001 (
b100010 $
b100010 )
b10001 '
#350000
1#
#360000
0#
b10010 "
b10010 (
b100100 $
b100100 )
b10010 '
#370000
1#
#380000
0#
b10011 "
b10011 (
b100110 $
b100110 )
b10011 '
#390000
1#
#400000
0#
b10100 "
b10100 (
b101000 $
b101000 )
b10100 '
#410000
1#
#420000
0#
b10101 "
b10101 (
b101010 $
b101010 )
b10101 '
#430000
1#
#440000
0#
b10110 "
b10110 (
b101100 $
b101100 )
b10110 '
#450000
1#
#460000
0#
b10111 "
b10111 (
b101110 $
b101110 )
b10111 '
#470000
1#
#480000
0#
b11000 "
b11000 (
b110000 $
b110000 )
b11000 '
#490000
1#
#500000
0#
b11001 "
b11001 (
b110010 $
b110010 )
b11001 '
#510000
1#
#520000
0#
b11010 "
b11010 (
b110100 $
b110100 )
b11010 '
#530000
1#
#540000
0#
b11011 "
b11011 (
b110110 $
b110110 )
b11011 '
#550000
1#
#560000
0#
b11100 "
b11100 (
b111000 $
b111000 )
b11100 '
#570000
1#
#580000
0#
b11101 "
b11101 (
b111010 $
b111010 )
b11101 '
#590000
1#
#600000
0#
b11110 "
b11110 (
b111100 $
b111100 )
b11110 '
#610000
1#
#620000
0#
b11111 "
b11111 (
b111110 $
b111110 )
b11111 '
#630000
1#
#640000
0#
b100000 "
b100000 (
b1000000 $
b1000000 )
b100000 '
#650000
1#
#660000
0#
b100001 "
b100001 (
b1000010 $
b1000010 )
b100001 '
#670000
1#
#680000
0#
b100010 "
b100010 (
b1000100 $
b1000100 )
b100010 '
#690000
1#
#700000
0#
b100011 "
b100011 (
b1000110 $
b1000110 )
b100011 '
#710000
1#
#720000
0#
b100100 "
b100100 (
b1001000 $
b1001000 )
b100100 '
#730000
1#
#740000
0#
b100101 "
b100101 (
b1001010 $
b1001010 )
b100101 '
#750000
1#
#760000
0#
b100110 "
b100110 (
b1001100 $
b1001100 )
b100110 '
#770000
1#
#780000
0#
b100111 "
b100111 (
b1001110 $
b1001110 )
b100111 '
#790000
1#
#800000
0#
b101000 "
b101000 (
b1010000 $
b1010000 )
b101000 '
#810000
1#
#820000
0#
b101001 "
b101001 (
b1010010 $
b1010010 )
b101001 '
#830000
1#
#840000
0#
b101010 "
b101010 (
b1010100 $
b1010100 )
b101010 '
#850000
1#
#860000
0#
b101011 "
b101011 (
b1010110 $
b1010110 )
b101011 '
#870000
1#
#880000
0#
b101100 "
b101100 (
b1011000 $
b1011000 )
b101100 '
#890000
1#
#900000
0#
b101101 "
b101101 (
b1011010 $
b1011010 )
b101101 '
#910000
1#
#920000
0#
b101110 "
b101110 (
b1011100 $
b1011100 )
b101110 '
#930000
1#
#940000
0#
b101111 "
b101111 (
b1011110 $
b1011110 )
b101111 '
#950000
1#
#960000
0#
b110000 "
b110000 (
b1100000 $
b1100000 )
b110000 '
#970000
1#
#980000
0#
b110001 "
b110001 (
b1100010 $
b1100010 )
b110001 '
#990000
1#
#1000000
0#
b110010 "
b110010 (
b1100100 $
b1100100 )
b110010 '
#1010000
1#
#1020000
0#
b110011 "
b110011 (
b1100110 $
b1100110 )
b110011 '
#1030000
1#
#1040000
0#
b110100 "
b110100 (
b1101000 $
b1101000 )
b110100 '
#1050000
1#
#1060000
0#
b110101 "
b110101 (
b1101010 $
b1101010 )
b110101 '
#1070000
1#
#1080000
0#
b110110 "
b110110 (
b1101100 $
b1101100 )
b110110 '
#1090000
1#
#1100000
0#
b110111 "
b110111 (
b1101110 $
b1101110 )
b110111 '
#1110000
1#
#1120000
0#
b111000 "
b111000 (
b1110000 $
b1110000 )
b111000 '
#1130000
1#
#1140000
0#
b111001 "
b111001 (
b1110010 $
b1110010 )
b111001 '
#1150000
1#
#1160000
0#
b111010 "
b111010 (
b1110100 $
b1110100 )
b111010 '
#1170000
1#
#1180000
0#
b111011 "
b111011 (
b1110110 $
b1110110 )
b111011 '
#1190000
1#
#1200000
0#
b111100 "
b111100 (
b1111000 $
b1111000 )
b111100 '
#1210000
1#
#1220000
0#
b111101 "
b111101 (
b1111010 $
b1111010 )
b111101 '
#1230000
1#
#1240000
0#
b111110 "
b111110 (
b1111100 $
b1111100 )
b111110 '
#1250000
1#
#1260000
0#
b111111 "
b111111 (
b1111110 $
b1111110 )
b111111 '
#1270000
1#
#1280000
0#
b1000000 "
b1000000 (
b10000000 $
b10000000 )
b1000000 '
#1290000
1#
#1300000
0#
b1000001 "
b1000001 (
b10000010 $
b10000010 )
b1000001 '
#1310000
1#
#1320000
0#
b1000010 "
b1000010 (
b10000100 $
b10000100 )
b1000010 '
#1330000
1#
#1340000
0#
b1000011 "
b1000011 (
b10000110 $
b10000110 )
b1000011 '
#1350000
1#
#1360000
0#
b1000100 "
b1000100 (
b10001000 $
b10001000 )
b1000100 '
#1370000
1#
#1380000
0#
b1000101 "
b1000101 (
b10001010 $
b10001010 )
b1000101 '
#1390000
1#
#1400000
0#
b1000110 "
b1000110 (
b10001100 $
b10001100 )
b1000110 '
#1410000
1#
#1420000
0#
b1000111 "
b1000111 (
b10001110 $
b10001110 )
b1000111 '
#1430000
1#
#1440000
0#
b1001000 "
b1001000 (
b10010000 $
b10010000 )
b1001000 '
#1450000
1#
#1460000
0#
b1001001 "
b1001001 (
b10010010 $
b10010010 )
b1001001 '
#1470000
1#
#1480000
0#
b1001010 "
b1001010 (
b10010100 $
b10010100 )
b1001010 '
#1490000
1#
#1500000
0#
b1001011 "
b1001011 (
b10010110 $
b10010110 )
b1001011 '
#1510000
1#
#1520000
0#
b1001100 "
b1001100 (
b10011000 $
b10011000 )
b1001100 '
#1530000
1#
#1540000
0#
b1001101 "
b1001101 (
b10011010 $
b10011010 )
b1001101 '
#1550000
1#
#1560000
0#
b1001110 "
b1001110 (
b10011100 $
b10011100 )
b1001110 '
#1570000
1#
#1580000
0#
b1001111 "
b1001111 (
b10011110 $
b10011110 )
b1001111 '
#1590000
1#
#1600000
0#
b1010000 "
b1010000 (
b10100000 $
b10100000 )
b1010000 '
#1610000
1#
#1620000
0#
b1010001 "
b1010001 (
b10100010 $
b10100010 )
b1010001 '
#1630000
1#
#1640000
0#
b1010010 "
b1010010 (
b10100100 $
b10100100 )
b1010010 '
#1650000
1#
#1660000
0#
b1010011 "
b1010011 (
b10100110 $
b10100110 )
b1010011 '
#1670000
1#
#1680000
0#
b1010100 "
b1010100 (
b10101000 $
b10101000 )
b1010100 '
#1690000
1#
#1700000
0#
b1010101 "
b1010101 (
b10101010 $
b10101010 )
b1010101 '
#1710000
1#
#1720000
0#
b1010110 "
b1010110 (
b10101100 $
b10101100 )
b1010110 '
#1730000
1#
#1740000
0#
b1010111 "
b1010111 (
b10101110 $
b10101110 )
b1010111 '
#1750000
1#
#1760000
0#
b1011000 "
b1011000 (
b10110000 $
b10110000 )
b1011000 '
#1770000
1#
#1780000
0#
b1011001 "
b1011001 (
b10110010 $
b10110010 )
b1011001 '
#1790000
1#
#1800000
0#
b1011010 "
b1011010 (
b10110100 $
b10110100 )
b1011010 '
#1810000
1#
#1820000
0#
b1011011 "
b1011011 (
b10110110 $
b10110110 )
b1011011 '
#1830000
1#
#1840000
0#
b1011100 "
b1011100 (
b10111000 $
b10111000 )
b1011100 '
#1850000
1#
#1860000
0#
b1011101 "
b1011101 (
b10111010 $
b10111010 )
b1011101 '
#1870000
1#
#1880000
0#
b1011110 "
b1011110 (
b10111100 $
b10111100 )
b1011110 '
#1890000
1#
#1900000
0#
b1011111 "
b1011111 (
b10111110 $
b10111110 )
b1011111 '
#1910000
1#
#1920000
0#
b1100000 "
b1100000 (
b11000000 $
b11000000 )
b1100000 '
#1930000
1#
#1940000
0#
b1100001 "
b1100001 (
b11000010 $
b11000010 )
b1100001 '
#1950000
1#
#1960000
0#
b1100010 "
b1100010 (
b11000100 $
b11000100 )
b1100010 '
#1970000
1#
#1980000
0#
b1100011 "
b1100011 (
b11000110 $
b11000110 )
b1100011 '
#1990000
1#
#2000000
0#
b1100100 "
b1100100 (
b11001000 $
b11001000 )
b1100100 '
#2010000
1#
#2020000
0#
b1100101 "
b1100101 (
b11001010 $
b11001010 )
b1100101 '
#2030000
1#
#2040000
0#
b1100110 "
b1100110 (
b11001100 $
b11001100 )
b1100110 '
#2050000
1#
#2060000
0#
b1100111 "
b1100111 (
b11001110 $
b11001110 )
b1100111 '
#2070000
1#
#2080000
0#
b1101000 "
b1101000 (
b11010000 $
b11010000 )
b1101000 '
#2090000
1#
#2100000
0#
b1101001 "
b1101001 (
b11010010 $
b11010010 )
b1101001 '
#2110000
1#
#2120000
0#
b1101010 "
b1101010 (
b11010100 $
b11010100 )
b1101010 '
#2130000
1#
#2140000
0#
b1101011 "
b1101011 (
b11010110 $
b11010110 )
b1101011 '
#2150000
1#
#2160000
0#
b1101100 "
b1101100 (
b11011000 $
b11011000 )
b1101100 '
#2170000
1#
#2180000
0#
b1101101 "
b1101101 (
b11011010 $
b11011010 )
b1101101 '
#2190000
1#
#2200000
0#
b1101110 "
b1101110 (
b11011100 $
b11011100 )
b1101110 '
#2210000
1#
#2220000
0#
b1101111 "
b1101111 (
b11011110 $
b11011110 )
b1101111 '
#2230000
1#
#2240000
0#
b1110000 "
b1110000 (
b11100000 $
b11100000 )
b1110000 '
#2250000
1#
#2260000
0#
b1110001 "
b1110001 (
b11100010 $
b11100010 )
b1110001 '
#2270000
1#
#2280000
0#
b1110010 "
b1110010 (
b11100100 $
b11100100 )
b1110010 '
#2290000
1#
#2300000
0#
b1110011 "
b1110011 (
b11100110 $
b11100110 )
b1110011 '
#2310000
1#
#2320000
0#
b1110100 "
b1110100 (
b11101000 $
b11101000 )
b1110100 '
#2330000
1#
#2340000
0#
b1110101 "
b1110101 (
b11101010 $
b11101010 )
b1110101 '
#2350000
1#
#2360000
0#
b1110110 "
b1110110 (
b11101100 $
b11101100 )
b1110110 '
#2370000
1#
#2380000
0#
b1110111 "
b1110111 (
b11101110 $
b11101110 )
b1110111 '
#2390000
1#
#2400000
0#
b1111000 "
b1111000 (
b11110000 $
b11110000 )
b1111000 '
#2410000
1#
#2420000
0#
b1111001 "
b1111001 (
b11110010 $
b11110010 )
b1111001 '
#2430000
1#
#2440000
0#
b1111010 "
b1111010 (
b11110100 $
b11110100 )
b1111010 '
#2450000
1#
#2460000
0#
b1111011 "
b1111011 (
b11110110 $
b11110110 )
b1111011 '
#2470000
1#
#2480000
0#
b1111100 "
b1111100 (
b11111000 $
b11111000 )
b1111100 '
#2490000
1#
#2500000
0#
b1111101 "
b1111101 (
b11111010 $
b11111010 )
b1111101 '
#2510000
1#
#2520000
0#
b1111110 "
b1111110 (
b11111100 $
b11111100 )
b1111110 '
#2530000
1#
#2540000
0#
b1111111 "
b1111111 (
b11111110 $
b11111110 )
b1111111 '
#2550000
1#
#2560000
0#
b10000000 "
b10000000 (
b0 $
b0 )
b10000000 '
#2570000
1#
#2580000
0#
b10000001 "
b10000001 (
b10 $
b10 )
b10000001 '
#2590000
1#
#2600000
0#
b10000010 "
b10000010 (
b100 $
b100 )
b10000010 '
#2610000
1#
#2620000
0#
b10000011 "
b10000011 (
b110 $
b110 )
b10000011 '
#2630000
1#
#2640000
0#
b10000100 "
b10000100 (
b1000 $
b1000 )
b10000100 '
#2650000
1#
#2660000
0#
b10000101 "
b10000101 (
b1010 $
b1010 )
b10000101 '
#2670000
1#
#2680000
0#
b10000110 "
b10000110 (
b1100 $
b1100 )
b10000110 '
#2690000
1#
#2700000
0#
b10000111 "
b10000111 (
b1110 $
b1110 )
b10000111 '
#2710000
1#
#2720000
0#
b10001000 "
b10001000 (
b10000 $
b10000 )
b10001000 '
#2730000
1#
#2740000
0#
b10001001 "
b10001001 (
b10010 $
b10010 )
b10001001 '
#2750000
1#
#2760000
0#
b10001010 "
b10001010 (
b10100 $
b10100 )
b10001010 '
#2770000
1#
#2780000
0#
b10001011 "
b10001011 (
b10110 $
b10110 )
b10001011 '
#2790000
1#
#2800000
0#
b10001100 "
b10001100 (
b11000 $
b11000 )
b10001100 '
#2810000
1#
#2820000
0#
b10001101 "
b10001101 (
b11010 $
b11010 )
b10001101 '
#2830000
1#
#2840000
0#
b10001110 "
b10001110 (
b11100 $
b11100 )
b10001110 '
#2850000
1#
#2860000
0#
b10001111 "
b10001111 (
b11110 $
b11110 )
b10001111 '
#2870000
1#
#2880000
0#
b10010000 "
b10010000 (
b100000 $
b100000 )
b10010000 '
#2890000
1#
#2900000
0#
b10010001 "
b10010001 (
b100010 $
b100010 )
b10010001 '
#2910000
1#
#2920000
0#
b10010010 "
b10010010 (
b100100 $
b100100 )
b10010010 '
#2930000
1#
#2940000
0#
b10010011 "
b10010011 (
b100110 $
b100110 )
b10010011 '
#2950000
1#
#2960000
0#
b10010100 "
b10010100 (
b101000 $
b101000 )
b10010100 '
#2970000
1#
#2980000
0#
b10010101 "
b10010101 (
b101010 $
b101010 )
b10010101 '
#2990000
1#
#3000000
0#
b10010110 "
b10010110 (
b101100 $
b101100 )
b10010110 '
#3010000
1#
#3020000
0#
b10010111 "
b10010111 (
b101110 $
b101110 )
b10010111 '
#3030000
1#
#3040000
0#
b10011000 "
b10011000 (
b110000 $
b110000 )
b10011000 '
#3050000
1#
#3060000
0#
b10011001 "
b10011001 (
b110010 $
b110010 )
b10011001 '
#3070000
1#
#3080000
0#
b10011010 "
b10011010 (
b110100 $
b110100 )
b10011010 '
#3090000
1#
#3100000
0#
b10011011 "
b10011011 (
b110110 $
b110110 )
b10011011 '
#3110000
1#
#3120000
0#
b10011100 "
b10011100 (
b111000 $
b111000 )
b10011100 '
#3130000
1#
#3140000
0#
b10011101 "
b10011101 (
b111010 $
b111010 )
b10011101 '
#3150000
1#
#3160000
0#
b10011110 "
b10011110 (
b111100 $
b111100 )
b10011110 '
#3170000
1#
#3180000
0#
b10011111 "
b10011111 (
b111110 $
b111110 )
b10011111 '
#3190000
1#
#3200000
0#
b10100000 "
b10100000 (
b1000000 $
b1000000 )
b10100000 '
#3210000
1#
#3220000
0#
b10100001 "
b10100001 (
b1000010 $
b1000010 )
b10100001 '
#3230000
1#
#3240000
0#
b10100010 "
b10100010 (
b1000100 $
b1000100 )
b10100010 '
#3250000
1#
#3260000
0#
b10100011 "
b10100011 (
b1000110 $
b1000110 )
b10100011 '
#3270000
1#
#3280000
0#
b10100100 "
b10100100 (
b1001000 $
b1001000 )
b10100100 '
#3290000
1#
#3300000
0#
b10100101 "
b10100101 (
b1001010 $
b1001010 )
b10100101 '
#3310000
1#
#3320000
0#
b10100110 "
b10100110 (
b1001100 $
b1001100 )
b10100110 '
#3330000
1#
#3340000
0#
b10100111 "
b10100111 (
b1001110 $
b1001110 )
b10100111 '
#3350000
1#
#3360000
0#
b10101000 "
b10101000 (
b1010000 $
b1010000 )
b10101000 '
#3370000
1#
#3380000
0#
b10101001 "
b10101001 (
b1010010 $
b1010010 )
b10101001 '
#3390000
1#
#3400000
0#
b10101010 "
b10101010 (
b1010100 $
b1010100 )
b10101010 '
#3410000
1#
#3420000
0#
b10101011 "
b10101011 (
b1010110 $
b1010110 )
b10101011 '
#3430000
1#
#3440000
0#
b10101100 "
b10101100 (
b1011000 $
b1011000 )
b10101100 '
#3450000
1#
#3460000
0#
b10101101 "
b10101101 (
b1011010 $
b1011010 )
b10101101 '
#3470000
1#
#3480000
0#
b10101110 "
b10101110 (
b1011100 $
b1011100 )
b10101110 '
#3490000
1#
#3500000
0#
b10101111 "
b10101111 (
b1011110 $
b1011110 )
b10101111 '
#3510000
1#
#3520000
0#
b10110000 "
b10110000 (
b1100000 $
b1100000 )
b10110000 '
#3530000
1#
#3540000
0#
b10110001 "
b10110001 (
b1100010 $
b1100010 )
b10110001 '
#3550000
1#
#3560000
0#
b10110010 "
b10110010 (
b1100100 $
b1100100 )
b10110010 '
#3570000
1#
#3580000
0#
b10110011 "
b10110011 (
b1100110 $
b1100110 )
b10110011 '
#3590000
1#
#3600000
0#
b10110100 "
b10110100 (
b1101000 $
b1101000 )
b10110100 '
#3610000
1#
#3620000
0#
b10110101 "
b10110101 (
b1101010 $
b1101010 )
b10110101 '
#3630000
1#
#3640000
0#
b10110110 "
b10110110 (
b1101100 $
b1101100 )
b10110110 '
#3650000
1#
#3660000
0#
b10110111 "
b10110111 (
b1101110 $
b1101110 )
b10110111 '
#3670000
1#
#3680000
0#
b10111000 "
b10111000 (
b1110000 $
b1110000 )
b10111000 '
#3690000
1#
#3700000
0#
b10111001 "
b10111001 (
b1110010 $
b1110010 )
b10111001 '
#3710000
1#
#3720000
0#
b10111010 "
b10111010 (
b1110100 $
b1110100 )
b10111010 '
#3730000
1#
#3740000
0#
b10111011 "
b10111011 (
b1110110 $
b1110110 )
b10111011 '
#3750000
1#
#3760000
0#
b10111100 "
b10111100 (
b1111000 $
b1111000 )
b10111100 '
#3770000
1#
#3780000
0#
b10111101 "
b10111101 (
b1111010 $
b1111010 )
b10111101 '
#3790000
1#
#3800000
0#
b10111110 "
b10111110 (
b1111100 $
b1111100 )
b10111110 '
#3810000
1#
#3820000
0#
b10111111 "
b10111111 (
b1111110 $
b1111110 )
b10111111 '
#3830000
1#
#3840000
0#
b11000000 "
b11000000 (
b10000000 $
b10000000 )
b11000000 '
#3850000
1#
#3860000
0#
b11000001 "
b11000001 (
b10000010 $
b10000010 )
b11000001 '
#3870000
1#
#3880000
0#
b11000010 "
b11000010 (
b10000100 $
b10000100 )
b11000010 '
#3890000
1#
#3900000
0#
b11000011 "
b11000011 (
b10000110 $
b10000110 )
b11000011 '
#3910000
1#
#3920000
0#
b11000100 "
b11000100 (
b10001000 $
b10001000 )
b11000100 '
#3930000
1#
#3940000
0#
b11000101 "
b11000101 (
b10001010 $
b10001010 )
b11000101 '
#3950000
1#
#3960000
0#
b11000110 "
b11000110 (
b10001100 $
b10001100 )
b11000110 '
#3970000
1#
#3980000
0#
b11000111 "
b11000111 (
b10001110 $
b10001110 )
b11000111 '
#3990000
1#
#4000000
0#
b11001000 "
b11001000 (
b10010000 $
b10010000 )
b11001000 '
#4010000
1#
#4020000
0#
b11001001 "
b11001001 (
b10010010 $
b10010010 )
b11001001 '
#4030000
1#
#4040000
0#
b11001010 "
b11001010 (
b10010100 $
b10010100 )
b11001010 '
#4050000
1#
#4060000
0#
b11001011 "
b11001011 (
b10010110 $
b10010110 )
b11001011 '
#4070000
1#
#4080000
0#
b11001100 "
b11001100 (
b10011000 $
b10011000 )
b11001100 '
#4090000
1#
#4100000
0#
b11001101 "
b11001101 (
b10011010 $
b10011010 )
b11001101 '
#4110000
1#
#4120000
0#
b11001110 "
b11001110 (
b10011100 $
b10011100 )
b11001110 '
#4130000
1#
#4140000
0#
b11001111 "
b11001111 (
b10011110 $
b10011110 )
b11001111 '
#4150000
1#
#4160000
0#
b11010000 "
b11010000 (
b10100000 $
b10100000 )
b11010000 '
#4170000
1#
#4180000
0#
b11010001 "
b11010001 (
b10100010 $
b10100010 )
b11010001 '
#4190000
1#
#4200000
0#
b11010010 "
b11010010 (
b10100100 $
b10100100 )
b11010010 '
#4210000
1#
#4220000
0#
b11010011 "
b11010011 (
b10100110 $
b10100110 )
b11010011 '
#4230000
1#
#4240000
0#
b11010100 "
b11010100 (
b10101000 $
b10101000 )
b11010100 '
#4250000
1#
#4260000
0#
b11010101 "
b11010101 (
b10101010 $
b10101010 )
b11010101 '
#4270000
1#
#4280000
0#
b11010110 "
b11010110 (
b10101100 $
b10101100 )
b11010110 '
#4290000
1#
#4300000
0#
b11010111 "
b11010111 (
b10101110 $
b10101110 )
b11010111 '
#4310000
1#
#4320000
0#
b11011000 "
b11011000 (
b10110000 $
b10110000 )
b11011000 '
#4330000
1#
#4340000
0#
b11011001 "
b11011001 (
b10110010 $
b10110010 )
b11011001 '
#4350000
1#
#4360000
0#
b11011010 "
b11011010 (
b10110100 $
b10110100 )
b11011010 '
#4370000
1#
#4380000
0#
b11011011 "
b11011011 (
b10110110 $
b10110110 )
b11011011 '
#4390000
1#
#4400000
0#
b11011100 "
b11011100 (
b10111000 $
b10111000 )
b11011100 '
#4410000
1#
#4420000
0#
b11011101 "
b11011101 (
b10111010 $
b10111010 )
b11011101 '
#4430000
1#
#4440000
0#
b11011110 "
b11011110 (
b10111100 $
b10111100 )
b11011110 '
#4450000
1#
#4460000
0#
b11011111 "
b11011111 (
b10111110 $
b10111110 )
b11011111 '
#4470000
1#
#4480000
0#
b11100000 "
b11100000 (
b11000000 $
b11000000 )
b11100000 '
#4490000
1#
#4500000
0#
b11100001 "
b11100001 (
b11000010 $
b11000010 )
b11100001 '
#4510000
1#
#4520000
0#
b11100010 "
b11100010 (
b11000100 $
b11000100 )
b11100010 '
#4530000
1#
#4540000
0#
b11100011 "
b11100011 (
b11000110 $
b11000110 )
b11100011 '
#4550000
1#
#4560000
0#
b11100100 "
b11100100 (
b11001000 $
b11001000 )
b11100100 '
#4570000
1#
#4580000
0#
b11100101 "
b11100101 (
b11001010 $
b11001010 )
b11100101 '
#4590000
1#
#4600000
0#
b11100110 "
b11100110 (
b11001100 $
b11001100 )
b11100110 '
#4610000
1#
#4620000
0#
b11100111 "
b11100111 (
b11001110 $
b11001110 )
b11100111 '
#4630000
1#
#4640000
0#
b11101000 "
b11101000 (
b11010000 $
b11010000 )
b11101000 '
#4650000
1#
#4660000
0#
b11101001 "
b11101001 (
b11010010 $
b11010010 )
b11101001 '
#4670000
1#
#4680000
0#
b11101010 "
b11101010 (
b11010100 $
b11010100 )
b11101010 '
#4690000
1#
#4700000
0#
b11101011 "
b11101011 (
b11010110 $
b11010110 )
b11101011 '
#4710000
1#
#4720000
0#
b11101100 "
b11101100 (
b11011000 $
b11011000 )
b11101100 '
#4730000
1#
#4740000
0#
b11101101 "
b11101101 (
b11011010 $
b11011010 )
b11101101 '
#4750000
1#
#4760000
0#
b11101110 "
b11101110 (
b11011100 $
b11011100 )
b11101110 '
#4770000
1#
#4780000
0#
b11101111 "
b11101111 (
b11011110 $
b11011110 )
b11101111 '
#4790000
1#
#4800000
0#
b11110000 "
b11110000 (
b11100000 $
b11100000 )
b11110000 '
#4810000
1#
#4820000
0#
b11110001 "
b11110001 (
b11100010 $
b11100010 )
b11110001 '
#4830000
1#
#4840000
0#
b11110010 "
b11110010 (
b11100100 $
b11100100 )
b11110010 '
#4850000
1#
#4860000
0#
b11110011 "
b11110011 (
b11100110 $
b11100110 )
b11110011 '
#4870000
1#
#4880000
0#
b11110100 "
b11110100 (
b11101000 $
b11101000 )
b11110100 '
#4890000
1#
#4900000
0#
b11110101 "
b11110101 (
b11101010 $
b11101010 )
b11110101 '
#4910000
1#
#4920000
0#
b11110110 "
b11110110 (
b11101100 $
b11101100 )
b11110110 '
#4930000
1#
#4940000
0#
b11110111 "
b11110111 (
b11101110 $
b11101110 )
b11110111 '
#4950000
1#
#4960000
0#
b11111000 "
b11111000 (
b11110000 $
b11110000 )
b11111000 '
#4970000
1#
#4980000
0#
b11111001 "
b11111001 (
b11110010 $
b11110010 )
b11111001 '
#4990000
1#
#5000000
0#
b11111010 "
b11111010 (
b11110100 $
b11110100 )
b11111010 '
#5010000
1#
#5020000
0#
b11111011 "
b11111011 (
b11110110 $
b11110110 )
b11111011 '
#5030000
1#
#5040000
0#
b11111100 "
b11111100 (
b11111000 $
b11111000 )
b11111100 '
#5050000
1#
#5060000
0#
b11111101 "
b11111101 (
b11111010 $
b11111010 )
b11111101 '
#5070000
1#
#5080000
0#
b11111110 "
b11111110 (
b11111100 $
b11111100 )
b11111110 '
#5090000
1#
#5100000
0#
b11111111 "
b11111111 (
b11111110 $
b11111110 )
b11111111 '
#5110000
1#
#5120000
0#
b100000000 "
b100000000 (
b0 $
b0 )
b100000000 '
#5130000
1#
#5140000
0#
b100000001 "
b100000001 (
b10 $
b10 )
b100000001 '
#5150000
1#
#5160000
0#
b100000010 "
b100000010 (
b100 $
b100 )
b100000010 '
#5170000
1#
#5180000
0#
b100000011 "
b100000011 (
b110 $
b110 )
b100000011 '
#5190000
1#
#5200000
0#
b100000100 "
b100000100 (
b1000 $
b1000 )
b100000100 '
#5210000
1#
#5220000
0#
b100000101 "
b100000101 (
b1010 $
b1010 )
b100000101 '
#5230000
1#
#5240000
0#
b100000110 "
b100000110 (
b1100 $
b1100 )
b100000110 '
#5250000
1#
#5260000
0#
b100000111 "
b100000111 (
b1110 $
b1110 )
b100000111 '
#5270000
1#
#5280000
0#
b100001000 "
b100001000 (
b10000 $
b10000 )
b100001000 '
#5290000
1#
#5300000
0#
b100001001 "
b100001001 (
b10010 $
b10010 )
b100001001 '
#5310000
1#
#5320000
0#
b100001010 "
b100001010 (
b10100 $
b10100 )
b100001010 '
#5330000
1#
#5340000
0#
b100001011 "
b100001011 (
b10110 $
b10110 )
b100001011 '
#5350000
1#
#5360000
0#
b100001100 "
b100001100 (
b11000 $
b11000 )
b100001100 '
#5370000
1#
#5380000
0#
b100001101 "
b100001101 (
b11010 $
b11010 )
b100001101 '
#5390000
1#
#5400000
0#
b100001110 "
b100001110 (
b11100 $
b11100 )
b100001110 '
#5410000
1#
#5420000
0#
b100001111 "
b100001111 (
b11110 $
b11110 )
b100001111 '
#5430000
1#
#5440000
0#
b100010000 "
b100010000 (
b100000 $
b100000 )
b100010000 '
#5450000
1#
#5460000
0#
b100010001 "
b100010001 (
b100010 $
b100010 )
b100010001 '
#5470000
1#
#5480000
0#
b100010010 "
b100010010 (
b100100 $
b100100 )
b100010010 '
#5490000
1#
#5500000
0#
b100010011 "
b100010011 (
b100110 $
b100110 )
b100010011 '
#5510000
1#
#5520000
0#
b100010100 "
b100010100 (
b101000 $
b101000 )
b100010100 '
#5530000
1#
#5540000
0#
b100010101 "
b100010101 (
b101010 $
b101010 )
b100010101 '
#5550000
1#
#5560000
0#
b100010110 "
b100010110 (
b101100 $
b101100 )
b100010110 '
#5570000
1#
#5580000
0#
b100010111 "
b100010111 (
b101110 $
b101110 )
b100010111 '
#5590000
1#
#5600000
0#
b100011000 "
b100011000 (
b110000 $
b110000 )
b100011000 '
#5610000
1#
#5620000
0#
b100011001 "
b100011001 (
b110010 $
b110010 )
b100011001 '
#5630000
1#
#5640000
0#
b100011010 "
b100011010 (
b110100 $
b110100 )
b100011010 '
#5650000
1#
#5660000
0#
b100011011 "
b100011011 (
b110110 $
b110110 )
b100011011 '
#5670000
1#
#5680000
0#
b100011100 "
b100011100 (
b111000 $
b111000 )
b100011100 '
#5690000
1#
#5700000
0#
b100011101 "
b100011101 (
b111010 $
b111010 )
b100011101 '
#5710000
1#
