sequential/decode-stage/decode_stage.v
`timescale 1ns / 1ps
module register_file(clk,dstE, dstM, srcA , srcB , valA , valB , valM, valE);
    input clk;
    input [ 3:0] dstE;
    input [63:0] valE;
    input [ 3:0] dstM;
    input [63:0] valM;
    input [ 3:0] srcA;
    output reg[63:0] valA;
    input [ 3:0] srcB;
    output reg[63:0] valB;

    integer i,fd;
    parameter RAX = 4'h0;
    parameter RCX = 4'h1;
    parameter RDX = 4'h2;
    parameter RBX = 4'h3;
    parameter RSP = 4'h4;
    parameter RBP = 4'h5;
    parameter RSI = 4'h6;
    parameter RDI = 4'h7;
    parameter R8  = 4'h8;
    parameter R9  = 4'h9;
    parameter R10 = 4'ha;
    parameter R11 = 4'hb;
    parameter R12 = 4'hc;
    parameter R13 = 4'hd;
    parameter R14 = 4'he;
    parameter RNONE = 4'hf;

    reg [63:0] reg_mem [14:0];

    // initialize registers with 0's
    initial
    begin
    reg_mem[4'h0] <= 64'h0;
    reg_mem[4'h1] <= 64'h0;
    reg_mem[4'h2] <= 64'h0;
    reg_mem[4'h3] <= 64'h0;
    reg_mem[4'h4] <= 64'h0;
    reg_mem[4'h5] <= 64'h0;
    reg_mem[4'h6] <= 64'h0;
    reg_mem[4'h7] <= 64'h0;
    reg_mem[4'h8] <= 64'h0;
    reg_mem[4'h9] <= 64'h0;
    reg_mem[4'hA] <= 64'h0;
    reg_mem[4'hB] <= 64'h0;
    reg_mem[4'hC] <= 64'h0;
    reg_mem[4'hD] <= 64'h0;
    reg_mem[4'hE] <= 64'h0;
    end


    always @ (*)
    begin
        if(srcA!=RNONE)
        begin
            valA <= reg_mem[srcA] ;
        end
        
        if(srcB!=RNONE)
        begin
            valB <= reg_mem[srcB] ;
        end

    end
    always @(posedge clk)
    begin   
        
        if(dstE!=RNONE)
        begin
            reg_mem[dstE] <= valE;
            
        end
        
        if(dstM!=RNONE)
        begin
            reg_mem[dstM] <= valM;
        end

       
        $display("Current register status: \n");
        $display("rax : %d   rsp: %d   r8  : %d  r12 : %d \n",reg_mem[0],reg_mem[4],reg_mem[8],reg_mem[12]);
        $display("rcx : %d   rbp: %d   r9  : %d  r13 : %d \n",reg_mem[1],reg_mem[5],reg_mem[9],reg_mem[13]);
        $display("rdx : %d   rsi: %d   r10 : %d  r14 : %d \n",reg_mem[2],reg_mem[6],reg_mem[10],reg_mem[14]);
        $display("rbx : %d   rdi: %d   r11 : %d  F   : XX \n",reg_mem[3],reg_mem[7],reg_mem[11]);
        $display("\n\n");
        

    end


endmodule

module dstE_logic(icode,rB,dstE,Cnd,ifun);

    parameter RBX = 4'h3;
    parameter RSP = 4'h4;
    parameter RNONE = 4'hf;

    input[3:0] icode;
    input[3:0] rB;
    output reg [3:0] dstE;
    input Cnd;
    input[3:0] ifun;

    always @(icode,rB,ifun,Cnd)
    begin
        
        case (icode)
        4'h2:
            begin
                if(ifun == 4'h0)
                    dstE <= rB;
                else
                    begin
                        if(Cnd==1'b1)
                            dstE <= rB;
                        else
                            dstE <= 4'hF;
                    end           
            end
        4'h3 , 4'h6:
            begin
                dstE <= rB;
            end
        4'hA , 4'hB , 4'h8 , 4'h9 :
            begin
                dstE <= RSP;
            end
        default: dstE <= RNONE; // 4'hF;
        endcase

    end 
endmodule

module srcA_logic(icode,rA,srcA);

    parameter RSP = 4'h4;
    parameter RNONE = 4'hf;

    input[3:0] icode;
    input[3:0] rA;
    output reg[3:0] srcA;

    always @(icode,rA)
    begin
        
        case (icode)
        4'h2 , 4'h3 , 4'h6 , 4'hA:
            begin
                srcA <= rA;
            end
        4'hB , 4'h9  :
            begin
                srcA <= RSP;
            end
        default: srcA <= RNONE;
        endcase

    end 
endmodule


module dstM_logic(icode,rA,dstM);

    parameter RBX = 4'h3;
    parameter RSP = 4'h4;
    parameter RNONE = 4'hf;

    input[3:0] icode;
    input[3:0] rA;
    output reg[3:0] dstM;

    always @(icode,rA)
    begin
        
        case (icode)
        4'h5 , 4'hB:
            begin
                dstM <= rA;
            end
        default: dstM <= RNONE;
        endcase

    end 
endmodule

module srcB_logic(icode,rB,srcB);

    parameter RSP = 4'h4;
    parameter RNONE = 4'hf;

    input[3:0] icode;
    input[3:0] rB;
    output reg[3:0] srcB;

    always @(icode,rB)
    begin
        
        case (icode)
        4'h4 , 4'h5 , 4'h6:
            begin
                srcB <= rB;
            end
        4'h8 , 4'h9 ,4'hA , 4'hB:
            begin
                srcB <= RSP;
            end
        default: srcB <= RNONE;
        endcase

    end 
endmodule

sequential/decode-stage/decode_test.v
`timescale 1ns / 1ps

module decode_test;
    integer k;

    reg [63:0] valE;
    reg [3:0] rA; 
    reg [3:0] rB;
    reg [3:0] icode;
    wire [3:0] dstE;
    wire [3:0] dstM;
    wire [3:0] srcA;
    wire [3:0] srcB;
    wire [63:0] valA;
    wire [63:0] valB;
    reg [63:0] valM;
    wire Cnd;
    reg [3:0] ifun;
    reg clk;

    

    register_file reg_f(.clk(clk),.dstE(dstE), .dstM(dstM), .srcA(srcA) , .srcB(srcB) , .valA(valA) , .valB(valB) , .valM(valM), .valE(valE));
    dstE_logic dE_l(.icode(icode),.rB(rB),.dstE(dstE),.Cnd(Cnd),.ifun(ifun));
    srcA_logic sA_l(.icode(icode),.rA(rA),.srcA(srcA));
    srcB_logic sB_l(.icode(icode),.rB(rB),.srcB(srcB));
    dstM_logic dM_l(.icode(icode),.rA(rA),.dstM(dstM));

   

    
    initial begin
    clk <= 1'b0;
        $dumpfile("decode_test.vcd");
        $dumpvars(0,decode_test);
        #10;
        // irmovq
        icode <= 4'h3;
        ifun  <= 4'h0;
        rA <= 4'h0;
        rB <= 4'h3;
        valE <= 64'd525;
        valM <= 64'd300;
        #20;

        // moved 64'd525 to register rbx;

        icode <= 4'h3;
        ifun  <= 4'h0;
        rA <= 4'h3;
        rB <= 4'h0;
        valE <= 64'd300;
        valM <= 64'd300;
        #20;

        // moved 64'd300 to register rax;


        icode <= 4'h6;
        ifun  <= 4'h2;
        rA <= 4'h3;
        rB <= 4'h0;
        valE <= 64'd251;
        valM <= 64'd300;
        #20;

        icode <= 4'h6;
        ifun  <= 4'h2;
        rA <= 4'h3;
        rB <= 4'h0;
        valE <= 64'd252;
        valM <= 64'd300;
        #20;
        icode <= 4'h6;
        ifun  <= 4'h2;
        rA <= 4'h3;
        rB <= 4'h0;
        valE <= 64'd253;
        valM <= 64'd300;
        #20;

        //check memory to reg
        icode <= 4'h5;
        ifun  <= 4'h2;
        rA <= 4'h0;
        rB <= 4'h3;
        valE <= 64'd999;
        valM <= 64'd999;
       
        #20;
        icode <= 4'h6;
        ifun  <= 4'h2;
        rA <= 4'h0;
        rB <= 4'h3;
        valE <= 64'd253;
        valM <= 64'd300;
        
        #20 $finish;
        
   end
   always #10 clk = ~clk;
    
endmodule

sequential/decode-stage/decode_test.vcd
$date
	Wed Mar  3 21:26:16 2021
$end
$version
	Icarus Verilog
$end
$timescale
	1ps
$end
$scope module decode_test $end
$var wire 1 ! Cnd $end
$var wire 64 " valB [63:0] $end
$var wire 64 # valA [63:0] $end
$var wire 4 $ srcB [3:0] $end
$var wire 4 % srcA [3:0] $end
$var wire 4 & dstM [3:0] $end
$var wire 4 ' dstE [3:0] $end
$var reg 1 ( clk $end
$var reg 4 ) icode [3:0] $end
$var reg 4 * ifun [3:0] $end
$var reg 4 + rA [3:0] $end
$var reg 4 , rB [3:0] $end
$var reg 64 - valE [63:0] $end
$var reg 64 . valM [63:0] $end
$scope module dE_l $end
$var wire 1 ! Cnd $end
$var wire 4 / icode [3:0] $end
$var wire 4 0 ifun [3:0] $end
$var wire 4 1 rB [3:0] $end
$var reg 4 2 dstE [3:0] $end
$upscope $end
$scope module dM_l $end
$var wire 4 3 icode [3:0] $end
$var wire 4 4 rA [3:0] $end
$var reg 4 5 dstM [3:0] $end
$upscope $end
$scope module reg_f $end
$var wire 1 ( clk $end
$var wire 4 6 dstE [3:0] $end
$var wire 4 7 dstM [3:0] $end
$var wire 64 8 valE [63:0] $end
$var wire 64 9 valM [63:0] $end
$var wire 4 : srcB [3:0] $end
$var wire 4 ; srcA [3:0] $end
$var reg 64 < valA [63:0] $end
$var reg 64 = valB [63:0] $end
$upscope $end
$scope module sA_l $end
$var wire 4 > icode [3:0] $end
$var wire 4 ? rA [3:0] $end
$var reg 4 @ srcA [3:0] $end
$upscope $end
$scope module sB_l $end
$var wire 4 A icode [3:0] $end
$var wire 4 B rB [3:0] $end
$var reg 4 C srcB [3:0] $end
$upscope $end
$upscope $end
$enddefinitions $end
#0
$dumpvars
bx C
bx B
bx A
bx @
bx ?
bx >
bx =
bx <
bx ;
bx :
bx 9
bx 8
bx 7
b1111 6
bx 5
bx 4
bx 3
b1111 2
bx 1
bx 0
bx /
bx .
bx -
bx ,
bx +
bx *
bx )
0(
b1111 '
bx &
bx %
bx $
bx #
bx "
z!
$end
#10000
b11 '
b11 2
b11 6
b1111 &
b1111 5
b1111 7
b0 %
b0 ;
b0 @
b1111 $
b1111 :
b1111 C
b100101100 .
b100101100 9
b1000001101 -
b1000001101 8
b11 ,
b11 1
b11 B
b0 +
b0 4
b0 ?
b0 *
b0 0
b11 )
b11 /
b11 3
b11 >
b11 A
1(
#20000
0(
#30000
b1000001101 #
b1000001101 <
b0 '
b0 2
b0 6
b11 %
b11 ;
b11 @
b100101100 -
b100101100 8
b0 ,
b0 1
b0 B
b11 +
b11 4
b11 ?
1(
#40000
0(
#50000
b100101100 "
b100101100 =
b0 $
b0 :
b0 C
b11111011 -
b11111011 8
b10 *
b10 0
b110 )
b110 /
b110 3
b110 >
b110 A
1(
#60000
0(
#70000
b11111011 "
b11111011 =
b11111100 -
b11111100 8
1(
#80000
0(
#90000
b11111100 "
b11111100 =
b11111101 -
b11111101 8
1(
#100000
0(
#110000
b1000001101 "
b1000001101 =
b1111 '
b1111 2
b1111 6
b1111 %
b1111 ;
b1111 @
b0 &
b0 5
b0 7
b11 $
b11 :
b11 C
b1111100111 .
b1111100111 9
b1111100111 -
b1111100111 8
b11 ,
b11 1
b11 B
b0 +
b0 4
b0 ?
b101 )
b101 /
b101 3
b101 >
b101 A
1(
#120000
0(
#130000
b1111100111 #
b1111100111 <
b11 '
b11 2
b11 6
b1111 &
b1111 5
b1111 7
b0 %
b0 ;
b0 @
b100101100 .
b100101100 9
b11111101 -
b11111101 8
b110 )
b110 /
b110 3
b110 >
b110 A
1(
